zope.event-4.6-py3.9-nspkg.pth
zope/event/__init__.py
zope/event/classhandler.py
zope/event/tests.py
zope.event-4.6.dist-info/LICENSE.txt
zope.event-4.6.dist-info/METADATA
zope.event-4.6.dist-info/WHEEL
zope.event-4.6.dist-info/namespace_packages.txt
zope.event-4.6.dist-info/top_level.txt
zope.event-4.6.dist-info/RECORD
